fstrent_charts/__init__.py
fstrent_charts/fstrent_charts.py
fstrent_charts-1.1.0.dist-info/licenses/LICENSE
tests/__init__.py
tests/test_fstrent_charts.py
fstrent_charts-1.1.0.dist-info/METADATA
fstrent_charts-1.1.0.dist-info/WHEEL
fstrent_charts-1.1.0.dist-info/top_level.txt
fstrent_charts-1.1.0.dist-info/RECORD
