Metadata-Version: 2.4
Name: fstrent_charts
Version: 1.1.0
Summary: Color Chart options for terminal output
Home-page: https://github.com/wrm3/fstrent_charts
Author: FSTrent
Author-email: wrmartel3@gmail.com
Classifier: Programming Language :: Python :: 3
Classifier: License :: OSI Approved :: MIT License
Classifier: Operating System :: OS Independent
Requires-Python: >=3.6
License-File: LICENSE
Requires-Dist: colorama
Dynamic: author
Dynamic: author-email
Dynamic: classifier
Dynamic: description
Dynamic: description-content-type
Dynamic: home-page
Dynamic: license-file
Dynamic: requires-dist
Dynamic: requires-python
Dynamic: summary
